epmc_xml/__init__.py
epmc_xml/article.py
epmc_xml/fetch.py
epmc_xml-0.1.13.dist-info/LICENSE
epmc_xml-0.1.13.dist-info/METADATA
epmc_xml-0.1.13.dist-info/WHEEL
epmc_xml-0.1.13.dist-info/RECORD
